Metadata-Version: 2.4
Name: buildingid-nrel
Version: 2.2.0
Summary: Unique Building Identifier (UBID)
License: BSD-2-Clause
License-File: LICENSE.txt
Author: Mark Borkum
Author-email: mark.borkum@pnnl.gov
Requires-Python: >=3.9,<3.14
Classifier: Development Status :: 4 - Beta
Classifier: Intended Audience :: Developers
Classifier: License :: OSI Approved :: BSD License
Classifier: Programming Language :: Python :: 3
Classifier: Programming Language :: Python :: 3.9
Classifier: Programming Language :: Python :: 3.10
Classifier: Programming Language :: Python :: 3.11
Classifier: Programming Language :: Python :: 3.12
Classifier: Programming Language :: Python :: 3.13
Classifier: Topic :: Scientific/Engineering :: GIS
Requires-Dist: click (<8.2)
Requires-Dist: click_log (>=0.4.0,<0.5.0)
Requires-Dist: openlocationcode (>=1.0,<2.0)
Requires-Dist: pandas (>=2.2.2,<3)
Requires-Dist: pyqtree (>=1.0,<2.0)
Requires-Dist: shapely (<2.1)
Requires-Dist: tqdm (>=4.67,<5.0)
Project-URL: Homepage, https://github.com/SEED-platform/buildingid-nrel
Project-URL: Repository, https://github.com/SEED-platform/buildingid-nrel
